{
    "title": "Guide to getting verified",
    "link": "https://wise.com/help/articles/2949782/guide-to-getting-verified",
    "related_articles": [
        {
            "title": "Getting verified in Canada",
            "link": "https://wise.com/help/articles/2968884/getting-verified-in-canada?origin=related-article-2949782"
        },
        {
            "title": "How does Wise verify my address?",
            "link": "https://wise.com/help/articles/2949804/how-does-wise-verify-my-address?origin=related-article-2949782"
        },
        {
            "title": "Getting verified in Japan",
            "link": "https://wise.com/help/articles/2968293/getting-verified-in-japan?origin=related-article-2949782"
        },
        {
            "title": "What do I need to do to get my Wise card in the US?",
            "link": "https://wise.com/help/articles/2975581/what-do-i-need-to-do-to-get-my-wise-card-in-the-us?origin=related-article-2949782"
        },
        {
            "title": "How does Wise verify my identity?",
            "link": "https://wise.com/help/articles/2949801/how-does-wise-verify-my-identity?origin=related-article-2949782"
        }
    ]
}